[{"sidebar-main":["categories-2","recent-posts-2","calendar-2"],"sidebar-secondary":["calendar-3"],"sidebar-footer-1":["nav_menu-2"],"sidebar-footer-2":["nav_menu-3"],"sidebar-footer-3":["nav_menu-4"],"cherry-mega-menu":["categories-3","cherry_testimonials_widget-2","cherry-shortcodes-2"]},{"categories":{"2":{"title":"","count":0,"hierarchical":0,"dropdown":0},"3":{"mega_menu_columns":3,"mega_menu_parent_menu_id":34},"_multiwidget":1},"recent-posts":{"2":{"title":"","number":5},"_multiwidget":1},"calendar":{"2":{"title":""},"3":{"title":""},"_multiwidget":1},"nav_menu":{"2":{"title":"Design Portfolio","nav_menu":21,"nav_menu_slug":"design-portfolio"},"3":{"title":"Development Portfolio","nav_menu":22,"nav_menu_slug":"development-portfolio"},"4":{"title":"Marketing Portfolio","nav_menu":23,"nav_menu_slug":"marketing-portfolio"},"_multiwidget":1},"cherry_testimonials_widget":{"2":{"mega_menu_columns":3,"mega_menu_parent_menu_id":34,"title":"","specific_id":"","limit":2,"size":50,"content_length":15,"orderby":"date","order":"DESC","content_type":"part","display_author":true,"display_avatar":false,"custom_class":""},"_multiwidget":1},"cherry-shortcodes":{"2":{"mega_menu_columns":6,"mega_menu_parent_menu_id":34,"title":"OUR PROCESS","content":"<div class=\"top_info\">Fusce euismod consequat ante. Lorem ipsum dolor sit amet<\/div>\r\n\r\n[cherry_posts posts_per_page=\"2\" tax_operator=\"-1\" order=\"desc\" ignore_sticky_posts=\"no\" linked_title=\"no\" linked_image=\"no\" image_size=\"cherry-post3'\" content_type=\"part\" content_length=\"15\" button_text=\"Read More\" col_xs=\"12\" col_sm=\"12\" col_md=\"6\" col_lg=\"6\" template=\"posts_extra_light_menu.tmpl\"]"},"_multiwidget":1}},[]]